Metadata-Version: 2.1
Name: codewatch
Version: 1.0.0
Summary: Monitor and manage deeply customizable metrics about your python code using ASTs
Home-page: https://github.com/tophat/codewatch
License: UNKNOWN
Platform: UNKNOWN
Classifier: Development Status :: 4 - Beta
Classifier: Intended Audience :: Developers
Classifier: Natural Language :: English
Classifier: License :: OSI Approved :: Apache Software License
Classifier: Operating System :: OS Independent
Classifier: Programming Language :: Python
Classifier: Programming Language :: Python :: 3.6
Classifier: Programming Language :: Python :: 3.7
Classifier: Programming Language :: Python :: 3.8
Classifier: Programming Language :: Python :: Implementation :: CPython
Classifier: Topic :: Software Development :: Libraries 
Requires-Python: >=3.6, <3.9
Requires-Dist: astroid (>=2)
